corenlp_protobuf/CoreNLP_pb2.py
corenlp_protobuf/__init__.py
corenlp_protobuf-3.8.0.dist-info/DESCRIPTION.rst
corenlp_protobuf-3.8.0.dist-info/METADATA
corenlp_protobuf-3.8.0.dist-info/RECORD
corenlp_protobuf-3.8.0.dist-info/WHEEL
corenlp_protobuf-3.8.0.dist-info/metadata.json
corenlp_protobuf-3.8.0.dist-info/top_level.txt
