Metadata-Version: 1.1
Name: corenlp-protobuf
Version: 3.8.0
Summary: Python bindings for Stanford CoreNLP protobufs
Home-page: https://github.com/stanfordnlp/python-corenlp-protobuf
Author: Stanford NLP Group
Author-email: chaganty@cs.stanford.edu
License: MIT
Keywords: protobuf corenlp natural-language-processing nlp
Platform: UNKNOWN
Classifier: Development Status :: 5 - Production/Stable
Classifier: Intended Audience :: Developers
Classifier: Topic :: Software Development :: Object Brokering
Classifier: License :: OSI Approved :: MIT License
Classifier: Programming Language :: Python :: 2
Classifier: Programming Language :: Python :: 2.7
Classifier: Programming Language :: Python :: 3
Classifier: Programming Language :: Python :: 3.3
Classifier: Programming Language :: Python :: 3.4
Classifier: Programming Language :: Python :: 3.5
